{"stats":{"minecraft:used":{"pamhc2foodcore:chocolatedonutitem":1,"minecraft:stone_shovel":227,"minecraft:stone_pickaxe":45,"minecraft:oak_door":1,"minecraft:cobblestone":14,"minecraft:sweet_berries":10,"minecraft:crafting_table":1,"minecraft:furnace":2,"tconstruct:crafting_station":1,"pamhc2foodcore:chocolaterollitem":1},"minecraft:broken":{"minecraft:stone_shovel":1},"minecraft:picked_up":{"minecraft:crafting_table":2,"minecraft:clay_ball":96,"minecraft:sweet_berries":13,"minecraft:gravel":96,"minecraft:flint":9,"minecraft:sand":96,"minecraft:oak_log":64,"minecraft:spruce_log":1,"minecraft:coal":23,"minecraft:cobblestone":22},"minecraft:custom":{"minecraft:time_since_rest":53603,"minecraft:interact_with_furnace":13,"minecraft:sprint_one_cm":32615,"minecraft:walk_one_cm":42319,"minecraft:damage_taken":230,"minecraft:interact_with_crafting_table":2,"minecraft:swim_one_cm":5934,"minecraft:fly_one_cm":38949,"minecraft:open_chest":17,"minecraft:crouch_one_cm":1,"minecraft:play_one_minute":53603,"minecraft:sneak_time":272,"minecraft:walk_under_water_one_cm":8390,"minecraft:jump":314,"minecraft:leave_game":1,"minecraft:time_since_death":53603,"minecraft:walk_on_water_one_cm":16725,"minecraft:fall_one_cm":7294},"minecraft:mined":{"minecraft:sweet_berry_bush":7,"minecraft:spruce_log":1,"minecraft:clay":24,"minecraft:crafting_table":1,"minecraft:coal_ore":23,"minecraft:gravel":107,"minecraft:sand":96,"minecraft:stone":22},"minecraft:crafted":{"minecraft:oak_door":3,"tconstruct:pattern":3,"minecraft:oak_planks":12,"minecraft:stone_shovel":2,"minecraft:crafting_table":1,"tconstruct:crafting_station":1,"minecraft:spruce_planks":4,"minecraft:stick":8,"minecraft:stone_pickaxe":1,"minecraft:furnace":1,"tconstruct:grout":192,"minecraft:air":0}},"DataVersion":2586}